sorting_algorithms/__init__.py
sorting_algorithms/bubble_sort.py
sorting_algorithms/insertion_sort.py
sorting_algorithms/quick_sort.py
sorting_algorithms/selection_sort.py
sorting_algorithms-0.1.dist-info/METADATA
sorting_algorithms-0.1.dist-info/WHEEL
sorting_algorithms-0.1.dist-info/top_level.txt
sorting_algorithms-0.1.dist-info/RECORD
